gabarit/__init__.py
gabarit/template_api/__init__.py
gabarit/template_api/generate_api_project.py
gabarit/template_api/api_project/.coveragerc
gabarit/template_api/api_project/.dockerignore
gabarit/template_api/api_project/.env
gabarit/template_api/api_project/.gitignore
gabarit/template_api/api_project/Dockerfile
gabarit/template_api/api_project/README.md
gabarit/template_api/api_project/launch.sh
gabarit/template_api/api_project/makefile
gabarit/template_api/api_project/pyproject.toml
gabarit/template_api/api_project/setup.py
gabarit/template_api/api_project/package_name/__init__.py
gabarit/template_api/api_project/package_name/application.py
gabarit/template_api/api_project/package_name/core/__init__.py
gabarit/template_api/api_project/package_name/core/config.py
gabarit/template_api/api_project/package_name/core/logtools.py
gabarit/template_api/api_project/package_name/core/resources.py
gabarit/template_api/api_project/package_name/model/__init__.py
gabarit/template_api/api_project/package_name/model/model_base.py
gabarit/template_api/api_project/package_name/model/model_gabarit.py
gabarit/template_api/api_project/package_name/routers/__init__.py
gabarit/template_api/api_project/package_name/routers/functional.py
gabarit/template_api/api_project/package_name/routers/technical.py
gabarit/template_api/api_project/package_name/routers/schemas/__init__.py
gabarit/template_api/api_project/package_name/routers/schemas/functional.py
gabarit/template_api/api_project/package_name/routers/schemas/technical.py
gabarit/template_api/api_project/package_name/routers/schemas/utils.py
gabarit/template_api/api_project/tests/__init__.py
gabarit/template_api/api_project/tests/conftest.py
gabarit/template_api/api_project/tests/create_test_model.py
gabarit/template_api/api_project/tests/test_config.py
gabarit/template_api/api_project/tests/test_model.py
gabarit/template_api/api_project/tests/test_routers_functionnal.py
gabarit-1.3.3.dist-info/LICENSE
gabarit-1.3.3.dist-info/METADATA
gabarit-1.3.3.dist-info/WHEEL
gabarit-1.3.3.dist-info/entry_points.txt
gabarit-1.3.3.dist-info/top_level.txt
gabarit-1.3.3.dist-info/RECORD
