Metadata-Version: 2.1
Name: gabarit
Version: 1.3.3
Summary: Kickstart your AI project as code
Home-page: https://github.com/OSS-Pole-Emploi/gabarit
Author: Agence Data Services PE Nantes
Author-email: contactadsaiframeworks.00619@pole-emploi.fr
License: AGPL-3.0
Platform: windows
Platform: linux
Requires-Python: >=3.7
Requires-Dist: Jinja2 ==3.0.3
